guidata/__init__.py
guidata/config.py
guidata/configtools.py
guidata/env.py
guidata/guitest.py
guidata/qthelpers.py
guidata/userconfig.py
guidata/data/icons/apply.png
guidata/data/icons/arredit.png
guidata/data/icons/busy.png
guidata/data/icons/cell_edit.png
guidata/data/icons/copy.png
guidata/data/icons/copy_all.svg
guidata/data/icons/delete.png
guidata/data/icons/dictedit.png
guidata/data/icons/dtype.png
guidata/data/icons/edit.png
guidata/data/icons/exit.png
guidata/data/icons/expander_down.png
guidata/data/icons/expander_right.png
guidata/data/icons/export.svg
guidata/data/icons/file.png
guidata/data/icons/fileclose.png
guidata/data/icons/fileimport.png
guidata/data/icons/filenew.png
guidata/data/icons/fileopen.png
guidata/data/icons/filesave.png
guidata/data/icons/filesaveas.png
guidata/data/icons/format.svg
guidata/data/icons/guidata-banner.svg
guidata/data/icons/guidata-vertical.svg
guidata/data/icons/guidata.svg
guidata/data/icons/hist.png
guidata/data/icons/max.png
guidata/data/icons/min.png
guidata/data/icons/none.png
guidata/data/icons/not_found.png
guidata/data/icons/python.png
guidata/data/icons/quickview.png
guidata/data/icons/resize.svg
guidata/data/icons/save_all.png
guidata/data/icons/selection.png
guidata/data/icons/settings.png
guidata/data/icons/shape.png
guidata/data/icons/xmax.png
guidata/data/icons/xmin.png
guidata/data/icons/editors/copywop.png
guidata/data/icons/editors/edit.png
guidata/data/icons/editors/edit_add.png
guidata/data/icons/editors/editclear.png
guidata/data/icons/editors/editcopy.png
guidata/data/icons/editors/editcut.png
guidata/data/icons/editors/editdelete.png
guidata/data/icons/editors/editpaste.png
guidata/data/icons/editors/fileimport.png
guidata/data/icons/editors/filesave.png
guidata/data/icons/editors/imshow.png
guidata/data/icons/editors/insert.png
guidata/data/icons/editors/plot.png
guidata/data/icons/editors/rename.png
guidata/data/icons/editors/selectall.png
guidata/data/icons/filetypes/doc.png
guidata-3.14.0.dist-info/licenses/LICENSE
guidata-3.14.0.dist-info/METADATA
guidata-3.14.0.dist-info/WHEEL
guidata-3.14.0.dist-info/entry_points.txt
guidata-3.14.0.dist-info/top_level.txt
guidata-3.14.0.dist-info/RECORD
